teemi/__init__.py
teemi/_version.py
teemi/utils.py
teemi/build/PCR.py
teemi/build/__init__.py
teemi/build/containers_wells_picklists.py
teemi/build/robot_assembly.py
teemi/build/transformation.py
teemi/design/__init__.py
teemi/design/cloning.py
teemi/design/combinatorial_design.py
teemi/design/crispr_best.py
teemi/design/crispr_cas.py
teemi/design/crispri.py
teemi/design/fetch_sequences.py
teemi/design/gibson_cloning.py
teemi/design/retrieve_gene_homologs.py
teemi/design/sequence_finder.py
teemi/design/teselagen_helpers.py
teemi/learn/__init__.py
teemi/learn/auto_ml.py
teemi/learn/plotting.py
teemi/lims/__init__.py
teemi/lims/benchling_api.py
teemi/lims/csv_database.py
teemi/test/__init__.py
teemi/test/data_wrangling.py
teemi/test/genotyping.py
teemi-1.0.2.dist-info/licenses/AUTHORS.rst
teemi-1.0.2.dist-info/licenses/LICENSE
teemi-1.0.2.dist-info/METADATA
teemi-1.0.2.dist-info/WHEEL
teemi-1.0.2.dist-info/entry_points.txt
teemi-1.0.2.dist-info/top_level.txt
teemi-1.0.2.dist-info/RECORD
