Metadata-Version: 2.4
Name: teemi
Version: 1.0.2
Summary: A Python package for constructing microbial strains
Home-page: https://github.com/hiyama341/teemi
Author: Lucas Levassor
Author-email: lucaslevassor@gmail.com
License: MIT license
Keywords: teemi
Classifier: Development Status :: 2 - Pre-Alpha
Classifier: Intended Audience :: Developers
Classifier: License :: OSI Approved :: MIT License
Classifier: Natural Language :: English
Classifier: Programming Language :: Python :: 3.10
Classifier: Programming Language :: Python :: 3.11
Requires-Python: >=3.10
License-File: LICENSE
License-File: AUTHORS.rst
Requires-Dist: pydna>=5.5.0
Requires-Dist: pandas>=1.3.0
Requires-Dist: benchlingapi>=2.1.12
Requires-Dist: numpy>=1.21.0
Requires-Dist: biopython>=1.83
Requires-Dist: python-dotenv>=0.20.0
Requires-Dist: openpyxl>=3.0.9
Requires-Dist: wheel>=0.37.1
Requires-Dist: nbsphinx==0.9.2
Requires-Dist: pytest-cov==4.1.0
Requires-Dist: matplotlib>=3.5.1
Requires-Dist: intermine>=1.12.0
Requires-Dist: dnachisel>=3.2.10
Dynamic: author
Dynamic: author-email
Dynamic: classifier
Dynamic: description
Dynamic: description-content-type
Dynamic: home-page
Dynamic: keywords
Dynamic: license
Dynamic: license-file
Dynamic: requires-dist
Dynamic: requires-python
Dynamic: summary
